{"title": {"en": "Step One", "zh_cn": "\u6b65\u9aa4 1"}, "help": {"en": {"To move": "Press direction keys to move the cyan blocks around", "To win": "Fill all green symbols with the block shown", "What to do now": "Just move along the walls to the destination"}, "zh_cn": {"\u79fb\u52a8": "\u6309\u65b9\u5411\u952e\u6765\u628a\u9752\u8272\u65b9\u5757\u56db\u5904\u79fb\u52a8", "\u8d62": "\u628a\u6240\u6709\u7eff\u8272\u7b26\u53f7\u586b\u4e0a\u5b83\u663e\u793a\u7684\u65b9\u5757", "\u73b0\u5728\u8981\u505a\u7684": "\u53ea\u8981\u6cbf\u7740\u5899\u79fb\u52a8 \u5230\u8fbe\u7ec8\u70b9"}}, "next": -1, "perf": 13, "each": -1, "width": 8, "height": 6, "content": [[[3], [3], [3], [3], [0], [0], [0], [3]], [[3], [3], [3], [3], [0], [3], [0], [3]], [[3], [1], [0], [3], [0], [3], [[4, [1]]], [3]], [[3], [3], [0], [3], [0], [3], [3], [3]], [[3], [3], [0], [0], [0], [0], [0], [[5, [-6]]]], [[3], [3], [3], [3], [3], [3], [3], [3]]], "unlock_bonus": 0, "box_no_serial": false}