{"title": {"en": "Trembling", "zh_cn": "\u98a4\u6296"}, "help": {"en": {"W/A/S/D": "Move the level itself with these keys", "Marking": "Use the spaces well and not get stuck"}, "zh_cn": {"W/A/S/D": "\u7528\u8fd9\u4e9b\u952e\u6765\u79fb\u52a8\u5173\u5361\u672c\u8eab", "\u6807\u8bb0": "\u597d\u597d\u5229\u7528\u7a7a\u95f4, \u4e0d\u8981\u88ab\u5361\u4f4f"}}, "next": -1, "perf": 102, "each": -1, "width": 8, "height": 8, "content": [[[3], [3], [3], [3], [3], [3], [3], [3]], [[3], [0], [1], [3], [[4, [2]]], [0], [0], [3]], [[3], [0], [8], [0], [0], [3], [0], [3]], [[3], [[4, [8]]], [3], [0], [2], [[4, [8]]], [0], [3]], [[3], [0], [3], [0], [2], [0], [3], [3]], [[3], [0], [8], [0], [3], [3], [3], [3]], [[3], [3], [0], [0], [3], [3], [3], [3]], [[3], [3], [3], [[4, [2]]], [3], [3], [3], [3]]], "unlock_bonus": 0, "box_no_serial": false}